{
  "kind": "collectionType",
  "collectionName": "copy_block_pages",
  "info": {
    "singularName": "copy-block-page",
    "pluralName": "copy-block-pages",
    "displayName": "Copy - block page"
  },
  "options": {
    "draftAndPublish": true
  },
  "pluginOptions": {
    "versions": {
      "versioned": true
    },
    "i18n": {
      "localized": true
    }
  },
  "attributes": {
    "DescriptionHeader": {
      "pluginOptions": {
        "versions": {
          "versioned": true
        },
        "i18n": {
          "localized": true
        }
      },
      "type": "string",
      "required": true
    },
    "Authors": {
      "pluginOptions": {
        "versions": {
          "versioned": true
        },
        "i18n": {
          "localized": true
        }
      },
      "type": "string",
      "required": true
    },
    "DownloadContent": {
      "pluginOptions": {
        "versions": {
          "versioned": true
        },
        "i18n": {
          "localized": true
        }
      },
      "type": "string",
      "required": true
    },
    "PowerpointDownloadDescription": {
      "pluginOptions": {
        "versions": {
          "versioned": true
        },
        "i18n": {
          "localized": true
        }
      },
      "type": "string",
      "required": true
    },
    "DocxDownloadDescription": {
      "pluginOptions": {
        "versions": {
          "versioned": true
        },
        "i18n": {
          "localized": true
        }
      },
      "type": "string",
      "required": true
    },
    "IntermediateHeader": {
      "pluginOptions": {
        "versions": {
          "versioned": true
        },
        "i18n": {
          "localized": true
        }
      },
      "type": "string",
      "required": true
    },
    "WasCreatedAt": {
      "pluginOptions": {
        "versions": {
          "versioned": true
        },
        "i18n": {
          "localized": true
        }
      },
      "type": "string"
    },
    "WasUpdatedAt": {
      "pluginOptions": {
        "versions": {
          "versioned": true
        },
        "i18n": {
          "localized": true
        }
      },
      "type": "string"
    }
  }
}
